awt_quant/__init__.py
awt_quant/data_fetch/__init__.py
awt_quant/data_fetch/macro.py
awt_quant/data_fetch/yf_fetch.py
awt_quant/forecast/__init__.py
awt_quant/forecast/garch_forecast.py
awt_quant/forecast/lag_llama_forecast.py
awt_quant/forecast/macro_forecast.py
awt_quant/forecast/portfolio/__init__.py
awt_quant/forecast/portfolio/portfolio_forecast.py
awt_quant/forecast/portfolio/portfolio_simulations.py
awt_quant/forecast/stochastic/__init__.py
awt_quant/forecast/stochastic/pde_forecast.py
awt_quant/forecast/stochastic/portfolio/__init__.py
awt_quant/forecast/stochastic/portfolio/portfolio_forecast.py
awt_quant/forecast/stochastic/portfolio/portfolio_simulations.py
awt_quant/forecast/stochastic/run_simulations.py
awt_quant/forecast/stochastic/stochastic_likelihoods.py
awt_quant/forecast/stochastic/stochastic_models.py
awt_quant/portfolio/__init__.py
awt_quant/portfolio/multi_factor_analysis/DataCollector.py
awt_quant/portfolio/multi_factor_analysis/FactorConstructor.py
awt_quant/portfolio/multi_factor_analysis/KMeansClusterer.py
awt_quant/portfolio/multi_factor_analysis/LocalizedModel.py
awt_quant/portfolio/multi_factor_analysis/RandomForestFeatureSelector.py
awt_quant/portfolio/multi_factor_analysis/StressSensitivityAnalysis.py
awt_quant/portfolio/multi_factor_analysis/__init__.py
awt_quant/portfolio/multi_factor_analysis/main.py
awt_quant/portfolio/optimization/__init__.py
awt_quant/portfolio/optimization/optimize.py
awt_quant/risk/__init__.py
awt_quant/risk/tearsheet.py
awt_quant/utils.py
awt_quant-0.1.0.dist-info/METADATA
awt_quant-0.1.0.dist-info/WHEEL
awt_quant-0.1.0.dist-info/entry_points.txt
awt_quant-0.1.0.dist-info/RECORD
